cspyexamclient/__init__.py
cspyexamclient/main.py
cspyexamclient-0.1.10.dist-info/LICENSE
cspyexamclient-0.1.10.dist-info/METADATA
cspyexamclient-0.1.10.dist-info/WHEEL
cspyexamclient-0.1.10.dist-info/top_level.txt
cspyexamclient-0.1.10.dist-info/RECORD
