Metadata-Version: 2.1
Name: cspyexamclient
Version: 0.1.10
Summary: An internal tool for exam submission
Author: Obiwan
Author-email: quan.do@coderschool.vn
License-File: LICENSE
